CHANGES.txt
CONTRIBUTORS.txt
README.txt
setup.py
betahaus/__init__.py
betahaus.emaillogin.egg-info/PKG-INFO
betahaus.emaillogin.egg-info/SOURCES.txt
betahaus.emaillogin.egg-info/dependency_links.txt
betahaus.emaillogin.egg-info/entry_points.txt
betahaus.emaillogin.egg-info/namespace_packages.txt
betahaus.emaillogin.egg-info/not-zip-safe
betahaus.emaillogin.egg-info/requires.txt
betahaus.emaillogin.egg-info/top_level.txt
betahaus/emaillogin/__init__.py
betahaus/emaillogin/build-i18n
betahaus/emaillogin/catalog.py
betahaus/emaillogin/config.py
betahaus/emaillogin/configure.zcml
betahaus/emaillogin/interfaces.py
betahaus/emaillogin/overrides.zcml
betahaus/emaillogin/setuphandlers.py
betahaus/emaillogin/userdataschema.py
betahaus/emaillogin/Extensions/Install.py
betahaus/emaillogin/Extensions/__init__.py
betahaus/emaillogin/i18n/betahaus.emaillogin-sv.po
betahaus/emaillogin/i18n/generated.pot
betahaus/emaillogin/plugins/__init__.py
betahaus/emaillogin/plugins/emaillogin.py
betahaus/emaillogin/profiles/default/betahaus.emaillogin.various.txt
betahaus/emaillogin/profiles/default/import_steps.xml
betahaus/emaillogin/profiles/default/metadata.xml
betahaus/emaillogin/profiles/default/skins.xml
betahaus/emaillogin/profiles/extended/betahaus.emaillogin.extended.txt
betahaus/emaillogin/profiles/extended/import_steps.xml
betahaus/emaillogin/profiles/extended/toolset.xml
betahaus/emaillogin/skins/join_form_validate.vpy
betahaus/emaillogin/skins/mail_password.py
betahaus/emaillogin/skins/mail_password_form.pt
betahaus/emaillogin/skins/mail_password_form.pt.metadata
betahaus/emaillogin/skins/prefs_users_overview.cpt
betahaus/emaillogin/skins/prefs_users_overview.cpt.metadata
betahaus/emaillogin/skins/pwreset_form.cpt
betahaus/emaillogin/skins/pwreset_form.cpt.metadata
betahaus/emaillogin/skins/validate_email_allowed.vpy
betahaus/emaillogin/skins/validate_personalize.vpy
betahaus/emaillogin/skins/validate_pwreset_userid.vpy
betahaus/emaillogin/tests/__init__.py
betahaus/emaillogin/tests/admin.txt
betahaus/emaillogin/tests/base.py
betahaus/emaillogin/tests/browser.txt
betahaus/emaillogin/tests/test_catalog.py
betahaus/emaillogin/tests/test_doc.py
betahaus/emaillogin/tests/test_emaillogin.py
betahaus/emaillogin/tests/test_extension.py
betahaus/emaillogin/www/email.png
betahaus/emaillogin/www/emailloginAdd.zpt
docs/INSTALL.txt
