Metadata-Version: 1.0
Name: betahaus.emaillogin
Version: 0.6.1
Summary: Enables you to login using your emailaddress.
Home-page: http://pypi.python.org/pypi/betahaus.emaillogin
Author: Martin Lundwall
Author-email: martin@betahaus.net
License: GPL
Platform: UNKNOWN
Classifier: Framework :: Plone
Classifier: Intended Audience :: Developers
Classifier: Topic :: Software Development :: Libraries :: Python Modules
Classifier: License :: OSI Approved :: GNU General Public License (GPL)
